[
  {
    "openid": "user_pame96bsksr",
    "content": "你好",
    "type": "user",
    "id": 1,
    "createdAt": "2026-03-22T01:49:40.888Z",
    "updatedAt": "2026-03-22T01:49:40.888Z"
  },
  {
    "openid": "user_pame96bsksr",
    "content": "感谢您的咨询，我们会尽快回复您。",
    "type": "bot",
    "id": 2,
    "createdAt": "2026-03-22T01:49:40.889Z",
    "updatedAt": "2026-03-22T01:49:40.889Z"
  },
  {
    "openid": "user_ks18pi7ryna",
    "content": "你好",
    "type": "user",
    "id": 3,
    "createdAt": "2026-03-22T02:01:06.226Z",
    "updatedAt": "2026-03-22T02:01:06.226Z"
  },
  {
    "openid": "user_ks18pi7ryna",
    "content": "感谢您的咨询，我们会尽快回复您。",
    "type": "bot",
    "id": 4,
    "createdAt": "2026-03-22T02:01:06.227Z",
    "updatedAt": "2026-03-22T02:01:06.227Z"
  },
  {
    "openid": "user_t41styboyg",
    "content": "你好",
    "type": "user",
    "id": 5,
    "createdAt": "2026-03-22T02:12:59.707Z",
    "updatedAt": "2026-03-22T02:12:59.707Z"
  },
  {
    "openid": "user_t41styboyg",
    "content": "感谢您的咨询，我们会尽快回复您。",
    "type": "bot",
    "id": 6,
    "createdAt": "2026-03-22T02:12:59.708Z",
    "updatedAt": "2026-03-22T02:12:59.708Z"
  },
  {
    "openid": "user_1j4a4lxag5j",
    "content": "你好",
    "type": "user",
    "id": 7,
    "createdAt": "2026-03-22T02:28:52.356Z",
    "updatedAt": "2026-03-22T02:28:52.356Z"
  },
  {
    "openid": "user_1j4a4lxag5j",
    "content": "感谢您的咨询，我们会尽快回复您。",
    "type": "bot",
    "id": 8,
    "createdAt": "2026-03-22T02:28:52.356Z",
    "updatedAt": "2026-03-22T02:28:52.356Z"
  },
  {
    "openid": "user_5oumdw77o1m",
    "content": "你好",
    "type": "user",
    "id": 9,
    "createdAt": "2026-03-22T02:29:03.435Z",
    "updatedAt": "2026-03-22T02:29:03.435Z"
  },
  {
    "openid": "user_5oumdw77o1m",
    "content": "感谢您的咨询，我们会尽快回复您。",
    "type": "bot",
    "id": 10,
    "createdAt": "2026-03-22T02:29:03.435Z",
    "updatedAt": "2026-03-22T02:29:03.435Z"
  },
  {
    "openid": "user_56nodnmzlea",
    "content": "你好",
    "type": "user",
    "id": 11,
    "createdAt": "2026-03-22T02:29:13.684Z",
    "updatedAt": "2026-03-22T02:29:13.684Z"
  },
  {
    "openid": "user_56nodnmzlea",
    "content": "感谢您的咨询，我们会尽快回复您。",
    "type": "bot",
    "id": 12,
    "createdAt": "2026-03-22T02:29:13.685Z",
    "updatedAt": "2026-03-22T02:29:13.685Z"
  },
  {
    "openid": "user_1yxo70yujuu",
    "content": "你好",
    "type": "user",
    "id": 13,
    "createdAt": "2026-03-22T02:29:33.104Z",
    "updatedAt": "2026-03-22T02:29:33.104Z"
  },
  {
    "openid": "user_1yxo70yujuu",
    "content": "感谢您的咨询，我们会尽快回复您。",
    "type": "bot",
    "id": 14,
    "createdAt": "2026-03-22T02:29:33.104Z",
    "updatedAt": "2026-03-22T02:29:33.104Z"
  },
  {
    "openid": "user_9bh4y65yrk8",
    "content": "你好",
    "type": "user",
    "id": 15,
    "createdAt": "2026-03-22T02:29:43.418Z",
    "updatedAt": "2026-03-22T02:29:43.418Z"
  },
  {
    "openid": "user_9bh4y65yrk8",
    "content": "感谢您的咨询，我们会尽快回复您。",
    "type": "bot",
    "id": 16,
    "createdAt": "2026-03-22T02:29:43.418Z",
    "updatedAt": "2026-03-22T02:29:43.418Z"
  },
  {
    "openid": "user_4radzcdm7g",
    "content": "你好",
    "type": "user",
    "id": 17,
    "createdAt": "2026-03-22T02:29:54.247Z",
    "updatedAt": "2026-03-22T02:29:54.247Z"
  },
  {
    "openid": "user_4radzcdm7g",
    "content": "感谢您的咨询，我们会尽快回复您。",
    "type": "bot",
    "id": 18,
    "createdAt": "2026-03-22T02:29:54.248Z",
    "updatedAt": "2026-03-22T02:29:54.248Z"
  },
  {
    "openid": "user_ennzip072wq",
    "content": "你好",
    "type": "user",
    "id": 19,
    "createdAt": "2026-03-22T02:30:06.251Z",
    "updatedAt": "2026-03-22T02:30:06.251Z"
  },
  {
    "openid": "user_ennzip072wq",
    "content": "感谢您的咨询，我们会尽快回复您。",
    "type": "bot",
    "id": 20,
    "createdAt": "2026-03-22T02:30:06.252Z",
    "updatedAt": "2026-03-22T02:30:06.252Z"
  },
  {
    "openid": "user_jkyvazw10yq",
    "content": "你好",
    "type": "user",
    "id": 21,
    "createdAt": "2026-03-22T02:30:17.762Z",
    "updatedAt": "2026-03-22T02:30:17.762Z"
  },
  {
    "openid": "user_jkyvazw10yq",
    "content": "感谢您的咨询，我们会尽快回复您。",
    "type": "bot",
    "id": 22,
    "createdAt": "2026-03-22T02:30:17.764Z",
    "updatedAt": "2026-03-22T02:30:17.764Z"
  },
  {
    "openid": "user_z44s4mn0q5q",
    "content": "你好",
    "type": "user",
    "id": 23,
    "createdAt": "2026-03-22T02:30:31.032Z",
    "updatedAt": "2026-03-22T02:30:31.032Z"
  },
  {
    "openid": "user_z44s4mn0q5q",
    "content": "感谢您的咨询，我们会尽快回复您。",
    "type": "bot",
    "id": 24,
    "createdAt": "2026-03-22T02:30:31.033Z",
    "updatedAt": "2026-03-22T02:30:31.033Z"
  },
  {
    "openid": "user_w9d6gvues4",
    "content": "你好",
    "type": "user",
    "id": 25,
    "createdAt": "2026-03-22T02:31:53.593Z",
    "updatedAt": "2026-03-22T02:31:53.593Z"
  },
  {
    "openid": "user_w9d6gvues4",
    "content": "感谢您的咨询，我们会尽快回复您。",
    "type": "bot",
    "id": 26,
    "createdAt": "2026-03-22T02:31:53.594Z",
    "updatedAt": "2026-03-22T02:31:53.595Z"
  },
  {
    "openid": "user_fnexgjlly6",
    "content": "你好",
    "type": "user",
    "id": 27,
    "createdAt": "2026-03-22T02:35:05.489Z",
    "updatedAt": "2026-03-22T02:35:05.489Z"
  },
  {
    "openid": "user_fnexgjlly6",
    "content": "感谢您的咨询，我们会尽快回复您。",
    "type": "bot",
    "id": 28,
    "createdAt": "2026-03-22T02:35:05.491Z",
    "updatedAt": "2026-03-22T02:35:05.491Z"
  },
  {
    "openid": "user_8ptjq6tw2e",
    "content": "你好",
    "type": "user",
    "id": 29,
    "createdAt": "2026-03-22T02:35:29.309Z",
    "updatedAt": "2026-03-22T02:35:29.309Z"
  },
  {
    "openid": "user_8ptjq6tw2e",
    "content": "感谢您的咨询，我们会尽快回复您。",
    "type": "bot",
    "id": 30,
    "createdAt": "2026-03-22T02:35:29.310Z",
    "updatedAt": "2026-03-22T02:35:29.310Z"
  },
  {
    "openid": "user_cftqljqqzhl",
    "content": "你好",
    "type": "user",
    "id": 31,
    "createdAt": "2026-03-22T02:36:58.050Z",
    "updatedAt": "2026-03-22T02:36:58.050Z"
  },
  {
    "openid": "user_cftqljqqzhl",
    "content": "感谢您的咨询，我们会尽快回复您。",
    "type": "bot",
    "id": 32,
    "createdAt": "2026-03-22T02:36:58.050Z",
    "updatedAt": "2026-03-22T02:36:58.050Z"
  },
  {
    "openid": "user_p146xolyhhq",
    "content": "你好",
    "type": "user",
    "id": 33,
    "createdAt": "2026-03-22T02:39:26.158Z",
    "updatedAt": "2026-03-22T02:39:26.159Z"
  },
  {
    "openid": "user_p146xolyhhq",
    "content": "感谢您的咨询，我们会尽快回复您。",
    "type": "bot",
    "id": 34,
    "createdAt": "2026-03-22T02:39:26.161Z",
    "updatedAt": "2026-03-22T02:39:26.161Z"
  }
]