[
  {
    "name": "当归",
    "alias": "全当归|秦当归|云当归",
    "cabinetNo": "A-01",
    "salePrice": 5,
    "stock": 21,
    "minValue": 500,
    "remark": "补血活血",
    "id": 1,
    "createdAt": "2026-03-19T21:44:50.964Z",
    "updatedAt": "2026-03-20T20:03:18.839Z"
  },
  {
    "name": "21321",
    "alias": "阿迪斯发士大夫",
    "unit": "克",
    "minValue": "0",
    "salePrice": "2130",
    "stock": 12,
    "isActive": true,
    "createdAt": "2026-03-20T01:42:20.679Z",
    "updatedAt": "2026-03-20T20:20:22.062Z",
    "id": 2,
    "cabinetNo": "",
    "remark": ""
  },
  {
    "name": "测试药材_1774009174577",
    "alias": "更新后的别名",
    "unit": "克",
    "minValue": "500",
    "cabinetNo": "B-01",
    "salePrice": "0.06",
    "remark": "测试备注",
    "isActive": true,
    "createdAt": "2026-03-20T20:19:36.242Z",
    "updatedAt": "2026-03-20T20:19:59.734Z",
    "id": 3,
    "stock": 500
  },
  {
    "name": "测试药材_1774009701527",
    "alias": "更新后的别名",
    "unit": "克",
    "minValue": 500,
    "cabinetNo": "B-01",
    "salePrice": 0.06,
    "remark": "测试备注",
    "isActive": true,
    "createdAt": "2026-03-20T20:28:22.717Z",
    "updatedAt": "2026-03-20T20:28:22.783Z",
    "id": 4,
    "stock": 500
  },
  {
    "name": "测试药材_1773946017030",
    "alias": "",
    "unit": "克",
    "minValue": 0,
    "salePrice": 0.06,
    "stock": 0,
    "isActive": true,
    "createdAt": "2026-03-20T20:28:22.764Z",
    "updatedAt": "2026-03-20T20:28:22.770Z",
    "id": 5
  },
  {
    "name": "测试药材_1774010296767",
    "alias": "更新后的别名",
    "unit": "克",
    "minValue": 500,
    "cabinetNo": "B-01",
    "salePrice": 0.06,
    "remark": "测试备注",
    "isActive": true,
    "createdAt": "2026-03-20T20:38:18.676Z",
    "updatedAt": "2026-03-20T20:38:18.743Z",
    "id": 6,
    "stock": 500
  },
  {
    "name": "测试药材_1773946189723",
    "alias": "",
    "unit": "克",
    "minValue": "0",
    "salePrice": "0.06",
    "stock": 0,
    "isActive": true,
    "createdAt": "2026-03-20T20:38:18.724Z",
    "updatedAt": "2026-03-20T21:50:03.169Z",
    "id": 7,
    "cabinetNo": "",
    "remark": ""
  },
  {
    "name": "测试药材_1774011082147",
    "alias": "更新后的别名",
    "unit": "克",
    "minValue": 500,
    "cabinetNo": "B-01",
    "salePrice": 0.06,
    "remark": "测试备注",
    "isActive": true,
    "createdAt": "2026-03-20T20:51:24.283Z",
    "updatedAt": "2026-03-20T20:51:24.348Z",
    "id": 8,
    "stock": 500
  },
  {
    "name": "测试药材_1773946803346",
    "alias": "",
    "unit": "克",
    "minValue": 0,
    "salePrice": 0.06,
    "stock": 100,
    "isActive": true,
    "createdAt": "2026-03-20T20:51:24.327Z",
    "updatedAt": "2026-03-20T21:50:03.207Z",
    "id": 9
  },
  {
    "name": "测试药材_1774012451383",
    "alias": "",
    "unit": "克",
    "minValue": "500",
    "cabinetNo": "B-01",
    "salePrice": "0.06",
    "remark": "测试备注",
    "isActive": true,
    "createdAt": "2026-03-20T21:14:13.065Z",
    "updatedAt": "2026-03-20T21:29:07.263Z",
    "id": 10,
    "stock": 500
  },
  {
    "name": "测试药材_1773946823913",
    "alias": "",
    "unit": "克",
    "minValue": 0,
    "salePrice": 0.06,
    "stock": 100,
    "isActive": true,
    "createdAt": "2026-03-20T21:14:13.113Z",
    "updatedAt": "2026-03-20T22:04:46.986Z",
    "id": 11
  },
  {
    "name": "测试药材_1774013435723",
    "alias": "更新后的别名",
    "unit": "克",
    "minValue": 500,
    "cabinetNo": "B-01",
    "salePrice": 0.06,
    "remark": "测试备注",
    "isActive": true,
    "createdAt": "2026-03-20T21:30:37.794Z",
    "updatedAt": "2026-03-20T21:30:37.869Z",
    "id": 12,
    "stock": 500
  },
  {
    "name": "测试药材_1773946840704",
    "alias": "",
    "unit": "克",
    "minValue": 0,
    "salePrice": 0.06,
    "stock": 100,
    "isActive": true,
    "createdAt": "2026-03-20T21:30:37.846Z",
    "updatedAt": "2026-03-20T22:09:44.937Z",
    "id": 13
  },
  {
    "name": "测试药材_1774014601294",
    "alias": "更新后的别名",
    "unit": "克",
    "minValue": 500,
    "cabinetNo": "B-01",
    "salePrice": 0.06,
    "remark": "测试备注",
    "isActive": true,
    "createdAt": "2026-03-20T21:50:03.137Z",
    "updatedAt": "2026-03-20T21:50:03.209Z",
    "id": 14,
    "stock": 500
  },
  {
    "name": "测试药材_1774015484870",
    "alias": "更新后的别名",
    "unit": "克",
    "minValue": 500,
    "cabinetNo": "B-01",
    "salePrice": 0.06,
    "remark": "测试备注",
    "isActive": true,
    "createdAt": "2026-03-20T22:04:46.910Z",
    "updatedAt": "2026-03-20T22:04:46.988Z",
    "id": 15,
    "stock": 500
  },
  {
    "name": "测试药材_1773946849401",
    "alias": "",
    "unit": "克",
    "minValue": 0,
    "salePrice": 0.06,
    "stock": 100,
    "isActive": true,
    "createdAt": "2026-03-20T22:04:46.959Z",
    "updatedAt": "2026-03-20T22:34:50.330Z",
    "id": 16
  },
  {
    "name": "测试药材_1774015782738",
    "alias": "更新后的别名",
    "unit": "克",
    "minValue": 500,
    "cabinetNo": "B-01",
    "salePrice": 0.06,
    "remark": "测试备注",
    "isActive": true,
    "createdAt": "2026-03-20T22:09:44.872Z",
    "updatedAt": "2026-03-20T22:09:44.939Z",
    "id": 17,
    "stock": 500
  },
  {
    "name": "测试药材_1773947018651",
    "alias": "",
    "unit": "克",
    "minValue": 0,
    "salePrice": 0.06,
    "stock": 0,
    "isActive": true,
    "createdAt": "2026-03-20T22:09:44.914Z",
    "updatedAt": "2026-03-20T22:09:44.920Z",
    "id": 18
  },
  {
    "name": "测试药材_1774017288656",
    "alias": "更新后的别名",
    "unit": "克",
    "minValue": 500,
    "cabinetNo": "B-01",
    "salePrice": 0.06,
    "remark": "测试备注",
    "isActive": true,
    "createdAt": "2026-03-20T22:34:50.249Z",
    "updatedAt": "2026-03-20T22:34:50.332Z",
    "id": 19,
    "stock": 500
  },
  {
    "name": "测试药材_1773947102030",
    "alias": "",
    "unit": "克",
    "minValue": 0,
    "salePrice": 0.06,
    "stock": 0,
    "isActive": true,
    "createdAt": "2026-03-20T22:34:50.303Z",
    "updatedAt": "2026-03-20T22:34:50.310Z",
    "id": 20
  }
]